xnxxdltagger/__init__.py
xnxxdltagger/main.py
xnxx_dl_tagger-0.0.4.dist-info/METADATA
xnxx_dl_tagger-0.0.4.dist-info/WHEEL
xnxx_dl_tagger-0.0.4.dist-info/entry_points.txt
xnxx_dl_tagger-0.0.4.dist-info/top_level.txt
xnxx_dl_tagger-0.0.4.dist-info/RECORD
